README.md
setup.py
pyqt_led/__init__.py
pyqt_led/pyqt_led.py
pyqt_led/test.py
pyqt_led.egg-info/PKG-INFO
pyqt_led.egg-info/SOURCES.txt
pyqt_led.egg-info/dependency_links.txt
pyqt_led.egg-info/not-zip-safe
pyqt_led.egg-info/requires.txt
pyqt_led.egg-info/top_level.txt