Metadata-Version: 2.1
Name: pyqt-led
Version: 0.0.5
Summary: Simple LED widget for PyQt5
Home-page: http://github.com/Neur1n/pyqt_led
Author: Jihang Li
Author-email: Jihang.Li@outlook.com
License: MIT
Platform: UNKNOWN
